Dist_Probability
