Metadata-Version: 1.0
Name: Dis-Probability
Version: 0.2
Summary: This is a fundamental package that helps compute both binomial and Gaussain probability
Home-page: UNKNOWN
Author: Oluwaseun Adeyo
Author-email: johnadeyo@hotmail.com
License: UNKNOWN
Platform: UNKNOWN
